odoo10_addon_contract_payment_mode-10.0.1.0.1-py2.7-nspkg.pth
odoo/addons/contract_payment_mode/README.rst
odoo/addons/contract_payment_mode/__init__.py
odoo/addons/contract_payment_mode/__manifest__.py
odoo/addons/contract_payment_mode/hooks.py
odoo/addons/contract_payment_mode/i18n/ca.po
odoo/addons/contract_payment_mode/i18n/de.po
odoo/addons/contract_payment_mode/i18n/el_GR.po
odoo/addons/contract_payment_mode/i18n/es.po
odoo/addons/contract_payment_mode/i18n/es_MX.po
odoo/addons/contract_payment_mode/i18n/fi.po
odoo/addons/contract_payment_mode/i18n/fr.po
odoo/addons/contract_payment_mode/i18n/gl.po
odoo/addons/contract_payment_mode/i18n/hr.po
odoo/addons/contract_payment_mode/i18n/hr_HR.po
odoo/addons/contract_payment_mode/i18n/hu.po
odoo/addons/contract_payment_mode/i18n/it.po
odoo/addons/contract_payment_mode/i18n/nl.po
odoo/addons/contract_payment_mode/i18n/pt.po
odoo/addons/contract_payment_mode/i18n/pt_BR.po
odoo/addons/contract_payment_mode/i18n/pt_PT.po
odoo/addons/contract_payment_mode/i18n/ro.po
odoo/addons/contract_payment_mode/i18n/sk_SK.po
odoo/addons/contract_payment_mode/i18n/sl.po
odoo/addons/contract_payment_mode/i18n/tr.po
odoo/addons/contract_payment_mode/i18n/tr_TR.po
odoo/addons/contract_payment_mode/i18n/zh_CN.po
odoo/addons/contract_payment_mode/models/__init__.py
odoo/addons/contract_payment_mode/models/contract.py
odoo/addons/contract_payment_mode/tests/__init__.py
odoo/addons/contract_payment_mode/tests/test_contract_payment.py
odoo/addons/contract_payment_mode/views/contract_view.xml
odoo10_addon_contract_payment_mode-10.0.1.0.1.dist-info/DESCRIPTION.rst
odoo10_addon_contract_payment_mode-10.0.1.0.1.dist-info/METADATA
odoo10_addon_contract_payment_mode-10.0.1.0.1.dist-info/RECORD
odoo10_addon_contract_payment_mode-10.0.1.0.1.dist-info/WHEEL
odoo10_addon_contract_payment_mode-10.0.1.0.1.dist-info/metadata.json
odoo10_addon_contract_payment_mode-10.0.1.0.1.dist-info/namespace_packages.txt
odoo10_addon_contract_payment_mode-10.0.1.0.1.dist-info/top_level.txt
